{
    "s-666-6b1422a467194da680b6792d5b4e5d7f": {
        "character": "Ace Visconti",
        "img": "assets/dbd/imgs/perks\\s-666-6b1422a467194da680b6792d5b4e5d7f.png",
        "description": {
            "mainEffect": "When retrieving an item from a chest, there's a 100% chance of finding an add-on of Very Rare Rarity or lower.",
            "secondaryEffect": "10/25/50% chance for a second add-on of Uncommon Rarity or lower.",
            "additionalEffect": "Allows you to keep any add-ons your item has equipped upon escaping."
        },
        "title": "Ace in the Hole"
    },
    "p-666-96dd72a5a1fc43d797ca35ba7baaad91": {
        "character": "Meg",
        "img": "assets/dbd/imgs/perks\\p-666-96dd72a5a1fc43d797ca35ba7baaad91.png",
        "description": {
            "mainEffect": "Instantly heal the equivalent of 1 health state.",
            "secondaryEffect": "Grants a +50% haste status effect for 3 seconds.",
            "additionalEffect": "Ignores the Exhausted status effect but causes it for 60/50/40 seconds."
        },
        "title": "Adrenaline"
    },
    "l-666-32717f7c302e48328008778099faa98a": {
        "character": "Jeff",
        "img": "assets/dbd/imgs/perks\\l-666-32717f7c302e48328008778099faa98a.png",
        "description": {
            "mainEffect": "The auras of the last 1/2/3 survivors are permanently revealed to you once certain conditions have been met.",
            "secondaryEffect": "Those survivors also have your aura revealed to them.",
            "additionalEffect": "Resets its effect once you are hooked."
        },
        "title": "Aftercare"
    },
    "o-666-8d54305a97e34de0830619dfbf20107c": {
        "character": "Feng Min",
        "img": "assets/dbd/imgs/perks\\o-666-8d54305a97e34de0830619dfbf20107c.png",
        "description": {
            "mainEffect": "Whenever the killer performs the break or damage action, their aura is revealed to you for 3/4/5 seconds.",
            "secondaryEffect": "",
            "additionalEffect": ""
        },
        "title": "Alert"
    },
    "f-666-20a74fb7fb0d49a284fcae2ae7cf9d74": {
        "character": "Yui Kimura",
        "img": "assets/dbd/imgs/perks\\f-666-20a74fb7fb0d49a284fcae2ae7cf9d74.png",
        "description": {
            "mainEffect": "Press and hold the active ability button to reset a dropped pallet to its upright position.",
            "secondaryEffect": "Grants the ability to see the auras of all dropped but not yet destroyed pallets.",
            "additionalEffect": ""
        },
        "title": "Any Means Necessary"
    },
    "l-666-98d1eec1208d49d3994ab965213c1e7a": {
        "character": "\u00c9lodie",
        "img": "assets/dbd/imgs/perks\\l-666-98d1eec1208d49d3994ab965213c1e7a.png",
        "description": {
            "mainEffect": "Start the trial with 3 tokens.",
            "secondaryEffect": "Consume 1 token to rummage through an already-opened chest for an item.",
            "additionalEffect": "Rummage through chests 40/60/80% faster, available once per chest."
        },
        "title": "Appraisal"
    },
    "b-666-11da5d1268664daab6511824be62e8a6": {
        "character": "Adam Francis",
        "img": "assets/dbd/imgs/perks\\b-666-11da5d1268664daab6511824be62e8a6.png",
        "description": {
            "mainEffect": "Start the trial with a -25% progression penalty for good skill checks while healing another survivor.",
            "secondaryEffect": "Succeeding a good skill check grants 1 token up to a maximum of 3/4/5 tokens.",
            "additionalEffect": "Each token grants a stackable progression bonus for succeeding a good skill check while healing."
        },
        "title": "Autodidact"
    },
    "g-666-e49ecbe1a9a24ad0838230db58afff54": {
        "character": "Steve Harrington",
        "img": "assets/dbd/imgs/perks\\g-666-e49ecbe1a9a24ad0838230db58afff54.png",
        "description": {
            "mainEffect": "When unhooking a survivor, the killer's aura is revealed to you for 8 seconds.",
            "secondaryEffect": "The unhooked survivor suppresses their scratch marks and pools of blood for 4/6/8 seconds.",
            "additionalEffect": "Increases their haste status effect by +7%."
        },
        "title": "Babysitter"
    },
    "e-666-4fe3376aa27c43669873c3db505d9a75": {
        "character": "Renato Lyra",
        "img": "assets/dbd/imgs/perks\\e-666-4fe3376aa27c43669873c3db505d9a75.png",
        "description": {
            "mainEffect": "Activates for 10 seconds when another survivor is picked up.",
            "secondaryEffect": "Starting to run while active grants a +50% haste status effect for 5 seconds.",
            "additionalEffect": "Causes the Exhausted status effect for 30/25/20 seconds."
        },
        "title": "Background Player"
    },
    "r-666-3603d2e8b6944fd3a6c5668026f02cc9": {
        "character": "Nea Karlsson",
        "img": "assets/dbd/imgs/perks\\r-666-3603d2e8b6944fd3a6c5668026f02cc9.png",
        "description": {
            "mainEffect": "Reduces the duration of stagger upon landing by -75%.",
            "secondaryEffect": "Suppresses all noises associated with falling.",
            "additionalEffect": "Grants a +50% haste status effect for 3 seconds upon landing, causing the Exhausted status effect for 60/50/40 seconds."
        },
        "title": "Balanced Landing"
    },
    "j-666-7f46c4a226c04e7fa7bbb58b9f671ac8": {
        "character": "Nancy Wheeler",
        "img": "assets/dbd/imgs/perks\\j-666-7f46c4a226c04e7fa7bbb58b9f671ac8.png",
        "description": {
            "mainEffect": "While repairing a generator, its aura is revealed to all other survivors within 32 meters.",
            "secondaryEffect": "If the killer downs a survivor while you are repairing, you see the auras of all other survivors for 8/9/10 seconds.",
            "additionalEffect": ""
        },
        "title": "Better Together"
    },
    "z-666-c8de105dc36a47579adbf3fb440a89ea": {
        "character": "Rebecca",
        "img": "assets/dbd/imgs/perks\\z-666-c8de105dc36a47579adbf3fb440a89ea.png",
        "description": {
            "mainEffect": "Upon completing a healing action, the healed survivor benefits from increased action speeds in healing, unlocking, cleansing, and blessing.",
            "secondaryEffect": "",
            "additionalEffect": "Increases their action speeds by 12/14/16% until the next time they take damage."
        },
        "title": "Better than New"
    },
    "n-666-986eedbe628a4310adc915e85a361d55": {
        "character": "Leon Scott Kennedy",
        "img": "assets/dbd/imgs/perks\\n-666-986eedbe628a4310adc915e85a361d55.png",
        "description": {
            "mainEffect": "When healing yourself or another, grunts of pain and healing noises are suppressed.",
            "secondaryEffect": "Failed healing skill checks do not trigger a loud noise notification.",
            "additionalEffect": "Applies only a 3/2/1% regression penalty."
        },
        "title": "Bite the Bullet"
    },
    "t-666-a4499662461e46f991f4519198c7e0db": {
        "character": "Jill",
        "img": "assets/dbd/imgs/perks\\t-666-a4499662461e46f991f4519198c7e0db.png",
        "description": {
            "main_effect": "After repairing Generators for a total of 50%, Blast Mine activates.",
            "secondary_effect": "Press the Active Ability button near a partially progressed Generator to install a Trap, which stays active for 100/110/120 seconds.",
            "additional_effect": "When the Killer damages the Trapped Generator, its Trap explodes half-way through, stunning them and blinding anyone nearby. The Auras of Trapped Generators are revealed to all Survivors in yellow."
        },
        "title": "Blast Mine"
    },
    "b-666-1d66d601e78f4cb09598e2d27432e4a8": {
        "character": "Cheryl",
        "img": "assets/dbd/imgs/perks\\b-666-1d66d601e78f4cb09598e2d27432e4a8.png",
        "description": {
            "main_effect": "When either you or the Obsession become injured by any means, Blood Pact activates.",
            "secondary_effect": "Your Auras are constantly revealed to one another. Completing a Healing Action on the Obsession or having them complete one on yourself grants both a 5/6/7% Haste Status Effect.",
            "additional_effect": "This effect lasts for as long as you both remain within 16 metres of each other. Blood Pact deactivates after leaving this radius and is temporarily disabled if you are the Obsession."
        },
        "title": "Blood Pact"
    },
    "o-666-477c71c7ceef494d9fe4b43c03601154": {
        "character": "Renato",
        "img": "assets/dbd/imgs/perks\\o-666-477c71c7ceef494d9fe4b43c03601154.png",
        "description": {
            "main_effect": "Once you are one Hook away from instant death, Blood Rush activates.",
            "secondary_effect": "Press the Active Ability button to lose a Health State and instantly recover from the Exhausted Status Effect.",
            "additional_effect": "Causes the Broken Status Effect for 28/24/20 seconds while you are automatically healing back to Healthy. Blood Rush is disabled for the remainder of the Trial after use."
        },
        "title": "Blood Rush"
    },
    "y-666-e6561fa616ae42d9afa99cf1ba91d6d5": {
        "character": "Kate",
        "img": "assets/dbd/imgs/perks\\y-666-e6561fa616ae42d9afa99cf1ba91d6d5.png",
        "description": {
            "main_effect": "While being carried by the Killer, the following effects apply.",
            "secondary_effect": "Increases the strength of Struggle Effects on the Killer from your Wiggling by 60/70/80%. Suppresses the ability of the Killer to read the Auras of all Hooks within 16 metres.",
            "additional_effect": "Grants +33% of your current Wiggle progression upon landing if the Killer drops from height."
        },
        "title": "Boil Over"
    },
    "j-666-af906b220494438482d69e86957b0bc9": {
        "character": "Dwight",
        "img": "assets/dbd/imgs/perks\\j-666-af906b220494438482d69e86957b0bc9.png",
        "description": {
            "main_effect": "Unlocks potential in your Aura-reading ability.",
            "secondary_effect": "The Auras of all other Survivors within 20/28/36 metres of your location are revealed to you.",
            "additional_effect": "We have to work as a team, I need you to survive so that I can survive!"
        },
        "title": "Bond"
    },
    "n-666-4e753b9e962a4f0db72f859e561c0fff": {
        "character": "Mikaela",
        "img": "assets/dbd/imgs/perks\\n-666-4e753b9e962a4f0db72f859e561c0fff.png",
        "description": {
            "main_effect": "Press and hold the Active Ability button on a Dull or Hex Totem to bless it and create a Boon Totem.",
            "secondary_effect": "All Survivors benefit from increased Altruistic Healing speeds by 50/75/100% when not using a Med-Kit.",
            "additional_effect": "If a Survivor is injured, their Aura will be revealed to all other Survivors."
        },
        "title": "Boon: Circle of Healing"
    },
    "z-666-9f6a09d03136464fb9e2a2f6d9febbce": {
        "character": "Yoichi",
        "img": "assets/dbd/imgs/perks\\z-666-9f6a09d03136464fb9e2a2f6d9febbce.png",
        "description": {
            "main_effect": "Press and hold the Active Ability button on a Dull or Hex Totem to bless it and create a Boon Totem.",
            "secondary_effect": "All Survivors benefit from a 2% Haste Status Effect.",
            "additional_effect": "This effect lingers for 2/3/4 seconds after leaving the Boon Totem's range."
        },
        "title": "Boon: Dark Theory"
    },
    "n-666-98a17de55fd8476f8186583fd59fc9c7": {
        "character": "Jonah",
        "img": "assets/dbd/imgs/perks\\n-666-98a17de55fd8476f8186583fd59fc9c7.png",
        "description": {
            "main_effect": "Press and hold the Active Ability button on a Dull or Hex Totem to bless it and create a Boon Totem.",
            "secondary_effect": "All Survivors benefit from a 90/95/100% bonus to the Recovery speed.",
            "additional_effect": "Unlocks the Self-Recovery ability, allowing you to fully recover from the Dying State."
        },
        "title": "Boon: Exponential"
    },
    "q-666-a2513907529a4ce6a48a2188bf363cb6": {
        "character": "Alan",
        "img": "assets/dbd/imgs/perks\\q-666-a2513907529a4ce6a48a2188bf363cb6.png",
        "description": {
            "main_effect": "Press and hold the Active Ability button on a Dull or Hex Totem to bless it and create a Boon Totem.",
            "secondary_effect": "All Survivors benefit from the Auras of all Chests and Generators being revealed to them in blue.",
            "additional_effect": "Increases Action speeds for Blessing and Cleansing by 6/8/10% while you have a lit Boon Totem."
        },
        "title": "Boon: Illumination"
    },
    "d-666-cb5cde61f75944148a62ebd9d198bb96": {
        "character": "Mikaela",
        "img": "assets/dbd/imgs/perks\\d-666-cb5cde61f75944148a62ebd9d198bb96.png",
        "description": {
            "main_effect": "Press and hold the Active Ability button on a Dull or Hex Totem to bless it and create a Boon Totem.",
            "secondary_effect": "All Survivors benefit from Scratch Marks being suppressed.",
            "additional_effect": "Auras are hidden from The Killer. Both effects linger for 2/3/4 seconds after leaving the Boon Totem's range."
        },
        "title": "Boon: Shadow Step"
    },
    "s-666-8619487681c34bc384896f72dd48c680": {
        "character": "Bill",
        "img": "assets/dbd/imgs/perks\\s-666-8619487681c34bc384896f72dd48c680.png",
        "description": {
            "main_effect": "You are fuelled with unexpected energy when saving an ally from a Hook.",
            "secondary_effect": "Survivors you unhook benefit from the Endurance Status Effect.",
            "additional_effect": "Extends the duration of their Endurance Status Effect by 6/8/10 seconds. Extends the Haste Status Effect by 10 seconds."
        },
        "title": "Borrowed Time"
    },
    "n-666-bd0e15bce5034b2facb2784535557330": {
        "character": "Claudette",
        "img": "assets/dbd/imgs/perks\\n-666-bd0e15bce5034b2facb2784535557330.png",
        "description": {
            "main_effect": "Increases your Healing speed by 30/40/50%.",
            "secondary_effect": "Reduces the Healing efficiency of Med-Kits by -20%.",
            "additional_effect": "\"Basic Botany Knowledge could save your life someday\" \u2014 Claudette Morel."
        },
        "title": "Botany Knowledge"
    },
    "z-666-6355126d855541bda9f4ea313bd56946": {
        "character": "Jeff",
        "img": "assets/dbd/imgs/perks\\z-666-6355126d855541bda9f4ea313bd56946.png",
        "description": {
            "main_effect": "Each time you are unhooked or unhook yourself, the Hook breaks and the Killer's Aura is revealed to you for 4/5/6 seconds.",
            "secondary_effect": "A Hook broken by Breakdown takes 180 seconds to respawn.",
            "additional_effect": "\"Charge from the Belly of the Beast. Here's a sketch/painting on a piece of wood I saw by the side of this road. I felt like it got a story to tell. And it didn't waste its second chance.\" \u2014 Jeff, ink and oil wash on slice of wood, 12x16"
        },
        "title": "Breakdown"
    },
    "f-666-829c0056931643d58f37af5ef9202b41": {
        "character": "Yui",
        "img": "assets/dbd/imgs/perks\\f-666-829c0056931643d58f37af5ef9202b41.png",
        "description": {
            "main_effect": "Grants a 5/6/7 % Haste Status Effect when within 5 meters of a carried Survivor.",
            "secondary_effect": "Increases the Wiggle speed of the carried Survivor by +25%.",
            "additional_effect": "\"Come, we are going to rip our way out of this.\" \u2014 Yui Kimura"
        },
        "title": "Breakout"
    },
    "e-666-4ae19413a47a4690b3b3d8d533e80308": {
        "character": "Ash",
        "img": "assets/dbd/imgs/perks\\e-666-4ae19413a47a4690b3b3d8d533e80308.png",
        "description": {
            "main_effect": "Unlocks potential in your Aura-reading ability. When healing a Survivor in the Dying State, Buckle Up activates.",
            "secondary_effect": "Completing a Healing Action grants the dying Survivor a +50% Haste Status Effect for 3/4/5 seconds.",
            "additional_effect": "\"Ghost beaters never leave a man behind.\" \u2014 Ash Williams"
        },
        "title": "Buckle Up"
    },
    "s-666-9258d3a08adc44d6a35f5578c8ac5f00": {
        "character": "Felix",
        "img": "assets/dbd/imgs/perks\\s-666-9258d3a08adc44d6a35f5578c8ac5f00.png",
        "description": {
            "main_effect": "Hiding inside a Locker for 14/13/12 seconds while carrying a depleted Item will replenish its Charges to 99%.",
            "secondary_effect": "Each use of Built to Last reduces this percentage by -33%.",
            "additional_effect": "\"Architecture is the soul of civilisation.\" \u2014 Felix Richter"
        },
        "title": "Built to Last"
    },
    "o-666-1ef35a632ee94213a730be3528640570": {
        "character": "Jake",
        "img": "assets/dbd/imgs/perks\\o-666-1ef35a632ee94213a730be3528640570.png",
        "description": {
            "main_effect": "Prevents Crows from being alerted and suppresses the urge to scream from any cause.",
            "secondary_effect": "Suppresses all noises related to unlocking Chests and cleansing or blessing Totems.",
            "additional_effect": "Reduces their Interaction speed by 40/35/30%."
        },
        "title": "Calm Spirit"
    },
    "t-666-23cc1d4632bd40b0b4e3bfd80fd801cb": {
        "character": "Steve",
        "img": "assets/dbd/imgs/perks\\t-666-23cc1d4632bd40b0b4e3bfd80fd801cb.png",
        "description": {
            "main_effect": "Pauses the Struggle Phase timer for 26/30/34 seconds if another Survivor is within 16 meters of your Hook.",
            "secondary_effect": "Activates only in the Struggle Phase.",
            "additional_effect": "\"So, remember once you get in there... pretend like you don't care. There you go, you're learning my friend. You're learning.\" \u2014 Steve Harrington"
        },
        "title": "Camaraderie"
    },
    "r-666-2dc5bd36b3804a55bba60cacdc2ca1a0": {
        "character": "Alan",
        "img": "assets/dbd/imgs/perks\\r-666-2dc5bd36b3804a55bba60cacdc2ca1a0.png",
        "description": {
            "main_effect": "Shining a Flashlight grants a +50% Haste Status Effect.",
            "secondary_effect": "Blinding the Killer causes them to suffer from a -20% Hindered Status Effect for 6 seconds.",
            "additional_effect": "Has a cool-down of 80/70/60 seconds after blinding the Killer."
        },
        "title": "Champion of Light"
    },
    "x-666-a791c9ef046c4a9fbe89125191e159c7": {
        "character": "Ellen",
        "img": "assets/dbd/imgs/perks\\x-666-a791c9ef046c4a9fbe89125191e159c7.png",
        "description": {
            "main_effect": "After repairing Generators for a total of 70/60/50%, Chemical Trap activates.",
            "secondary_effect": "Install a Trap at a dropped Pallet, which will slow the Killer by -50% for 4 seconds when triggered.",
            "additional_effect": "Reveals the Auras of Trapped Pallets to all Survivors in yellow."
        },
        "title": "Chemical Trap"
    },
    "o-666-ed8f2bbbb5754418b3e372ede5ebeb64": {
        "character": "Mikaela",
        "img": "assets/dbd/imgs/perks\\o-666-ed8f2bbbb5754418b3e372ede5ebeb64.png",
        "description": {
            "main_effect": "After cleansing or blessing a Totem, Clairvoyance activates.",
            "secondary_effect": "See the Auras of various objects within 64 meters for 8/9/10 seconds.",
            "additional_effect": "\"Does anyone else see that? Just me?\" \u2014 Mikaela Reid"
        },
        "title": "Clairvoyance"
    },
    "o-666-3237266649504ab1bc71a67b8588a80b": {
        "character": "Jonah",
        "img": "assets/dbd/imgs/perks\\o-666-3237266649504ab1bc71a67b8588a80b.png",
        "description": {
            "main_effect": "Start with 1/2/3 Tokens and gain +1 per successful Great Skill Check, up to 5.",
            "secondary_effect": "Transforms a failed Skill Check of another Survivor into a Good Skill Check.",
            "additional_effect": "\"Cannot hurt to have another set of eyes on the problem.\" \u2014 Jonah Vasquez"
        },
        "title": "Corrective Action"
    },
    "c-666-3726ac85fc9743b192aef0d4b3a89222": {
        "character": "Jill",
        "img": "assets/dbd/imgs/perks\\c-666-3726ac85fc9743b192aef0d4b3a89222.png",
        "description": {
            "main_effect": "Cleanse Totems 20% faster.",
            "secondary_effect": "Gain a 20% Cleansing Speed bonus per cleansed Totem.",
            "additional_effect": "The Aura of the Totem farthest from you is revealed for 2/3/4 seconds."
        },
        "title": "Counterforce"
    },
    "w-666-6ffca2313b6e4913bb22cbb278792d63": {
        "character": "Thalita",
        "img": "assets/dbd/imgs/perks\\w-666-6ffca2313b6e4913bb22cbb278792d63.png",
        "description": {
            "main_effect": "After performing a Rush Vault action in a Chase, Cut Loose activates for 4/5/6 seconds.",
            "secondary_effect": "Suppresses the Loud Noise Notification and resets the timer when performing another Rush Vault.",
            "additional_effect": "\"I know how we can get out of here! Quick, this way!\" \u2014 Thalita Lyra"
        },
        "title": "Cut Loose"
    },
    "m-666-78d719e8173b4c6d956d9e53d79c508d": {
        "character": "Kate",
        "img": "assets/dbd/imgs/perks\\m-666-78d719e8173b4c6d956d9e53d79c508d.png",
        "description": {
            "main_effect": "Performing a Rush Vault or rushing out of a Locker prevents leaving Scratch Marks for 3 seconds.",
            "secondary_effect": "Has a cool-down of 60/50/40 seconds.",
            "additional_effect": "\"Another show's off and runnin', Dance with me, cuz there's a storm a commin'...\" \u2014 Kate Denson's \"Dance with Me\""
        },
        "title": "Dance With Me"
    },
    "w-666-c669eef4552a4123a23d1eb82d2addfa": {
        "character": "All",
        "img": "assets/dbd/imgs/perks\\w-666-c669eef4552a4123a23d1eb82d2addfa.png",
        "description": {
            "main_effect": "The Aura of the Killer is revealed to you for 5/7/10 seconds as soon as they come within 24 meters of your location after completing a Generator.",
            "secondary_effect": "Dark Sense deactivates after revealing the Killer's Aura.",
            "additional_effect": "Helps you understand how the Killer thinks."
        },
        "title": "Dark Sense"
    },
    "v-666-d507b1ff2eb24f8895513e34d8a7da9e": {
        "character": "David",
        "img": "assets/dbd/imgs/perks\\v-666-d507b1ff2eb24f8895513e34d8a7da9e.png",
        "description": {
            "main_effect": "Press the Active Ability button while running to gain the Endurance Status Effect for 0.5 seconds.",
            "secondary_effect": "Activates after being rescued from a Hook or self-unhooking. Deactivates after use.",
            "additional_effect": "Causes the Exhausted Status Effect for 60/50/40 seconds. Cannot be used when Exhausted."
        },
        "title": "Dead Hard"
    },
    "q-666-d7336244d3bb471ab41f63df2ef5b1e4": {
        "character": "Alan",
        "img": "assets/dbd/imgs/perks\\q-666-d7336244d3bb471ab41f63df2ef5b1e4.png",
        "description": {
            "main_effect": "Increases the Odds of triggering Skill Checks by 6/8/10% while repairing or healing.",
            "secondary_effect": "Causes Skill Checks to appear randomly.",
            "additional_effect": "Reduces penalty for missed Skill Checks by -50%."
        },
        "title": "Deadline"
    },
    "w-666-e3210e82463c49a280029da69cde5336": {
        "character": "\u00c9lodie",
        "img": "assets/dbd/imgs/perks\\w-666-e3210e82463c49a280029da69cde5336.png",
        "description": {
            "main_effect": "Interacting with a Locker while sprinting makes the Locker's doors swing open and close swiftly, feigning a Survivor's entry.",
            "secondary_effect": "Triggers a Loud Noise Notification and suppresses Scratch Marks and Pools of Blood for 3 seconds.",
            "additional_effect": "Has a cooldown of 60/50/40 seconds."
        },
        "title": "Deception"
    },
    "h-666-25581e3cc0634146984d66b862c4c9ce": {
        "character": "Laurie",
        "img": "assets/dbd/imgs/perks\\h-666-25581e3cc0634146984d66b862c4c9ce.png",
        "description": {
            "main_effect": "After unhooking or being unhooked, it activates for 40/50/60 seconds. Succeed a Skill Check to stab the Killer and escape from their grasp.",
            "secondary_effect": "Stuns the Killer for 4 seconds.",
            "additional_effect": "Causes you to become the next Obsession and disables after use."
        },
        "title": "Decisive Strike"
    },
    "n-666-9421dd6fb21d420c932160788e13dac4": {
        "character": "All",
        "img": "assets/dbd/imgs/perks\\n-666-9421dd6fb21d420c932160788e13dac4.png",
        "description": {
            "main_effect": "The Auras of the 3 closest Generators are revealed to you at all times.",
            "secondary_effect": "Increases Repair speed on these Generators by 4/5/6%.",
            "additional_effect": "If holding a Map, the Generators are automatically added to it."
        },
        "title": "Deja Vu"
    },
    "w-666-758482e8ad694849bdee481569dc3326": {
        "character": "Adam",
        "img": "assets/dbd/imgs/perks\\w-666-758482e8ad694849bdee481569dc3326.png",
        "description": {
            "main_effect": "After performing a Safe Hook Rescue on another Survivor, grants the ability to unhook yourself.",
            "secondary_effect": "After successfully unhooking yourself, you suffer from the Broken Status Effect for 100/80/60 seconds.",
            "additional_effect": "Not available during the second Hook stage or if you are hooked as the last Survivor."
        },
        "title": "Deliverance"
    },
    "f-666-811ddac49c2545769f1756c61a267b74": {
        "character": "Felix",
        "img": "assets/dbd/imgs/perks\\f-666-811ddac49c2545769f1756c61a267b74.png",
        "description": {
            "main_effect": "Increases Healing and Unhooking speeds by 10/12/14% for each injured, hooked, or dying Survivor.",
            "secondary_effect": "Up to a maximum of 40/48/56% speed increase.",
            "additional_effect": "Boosts action speeds during emergencies."
        },
        "title": "Desperate Measures"
    },
    "f-666-3cef08b96d0640cab62095e292ae51db": {
        "character": "David",
        "img": "assets/dbd/imgs/perks\\f-666-3cef08b96d0640cab62095e292ae51db.png",
        "description": {
            "main_effect": "Each time a Generator is completed, reveals the Auras of Generators, Chests, and Totems within 32/48/64 meters for 10 seconds.",
            "secondary_effect": "If holding a Map, any objects revealed are tracked.",
            "additional_effect": "Great for locating important items."
        },
        "title": "Detective's Hunch"
    },
    "y-666-1f3d050d91244491b738cfcc6991acac": {
        "character": "Jeff",
        "img": "assets/dbd/imgs/perks\\y-666-1f3d050d91244491b738cfcc6991acac.png",
        "description": {
            "main_effect": "Start the Trial with 3 Tokens. Prevents the Killer from reading your Aura for 6/8/10 seconds when consuming a Token.",
            "secondary_effect": "Suppresses Scratch Marks for the same duration.",
            "additional_effect": "Recharges 1 Token every 30 seconds within the Killer's Terror Radius."
        },
        "title": "Distortion"
    },
    "m-666-0aa356cd3a99445c84bb5dc7995f87b0": {
        "character": "Adam",
        "img": "assets/dbd/imgs/perks\\m-666-0aa356cd3a99445c84bb5dc7995f87b0.png",
        "description": {
            "main_effect": "After being within the Killer's Terror Radius for 40/35/30 seconds without being chased, activates.",
            "secondary_effect": "Press the Active Ability button while crouched to throw a pebble, creating a distraction for the Killer 20 meters away.",
            "additional_effect": "Triggers a Loud Noise Notification and creates fake Scratch Marks."
        },
        "title": "Diversion"
    },
    "n-666-8b5e880c4b1a4951891cfcc9bd45c244": {
        "character": "Nicolas",
        "img": "assets/dbd/imgs/perks\\n-666-8b5e880c4b1a4951891cfcc9bd45c244.png",
        "description": {
            "main_effect": "While healthy and running, press the Active Ability button to gain a 25% Haste Status Effect for 2 seconds.",
            "secondary_effect": "May cause an additional effect like Exposed Status, extended Haste, screaming, or gaining a rare item.",
            "additional_effect": "Causes the Exhausted Status Effect for 60/50/40 seconds."
        },
        "title": "Dramaturgy"
    },
    "t-666-a5f2d697de514656ab410bb57bf8a204": {
        "character": "Yoichi",
        "img": "assets/dbd/imgs/perks\\t-666-a5f2d697de514656ab410bb57bf8a204.png",
        "description": {
            "main_effect": "Injured Survivors can see your Aura when within 32/64/96 meters of you.",
            "secondary_effect": "You heal other Survivors 10% faster.",
            "additional_effect": "Helps coordinate healing efforts."
        },
        "title": "Empathic Connection"
    },
    "q-666-1b09aba373014605b66008c82ab5c9c1": {
        "character": "Claudette",
        "img": "assets/dbd/imgs/perks\\q-666-1b09aba373014605b66008c82ab5c9c1.png",
        "description": {
            "main_effect": "The Auras of injured or dying Survivors are revealed to you within 64/96/128 meters.",
            "secondary_effect": "Does not reveal the Aura of Survivors being carried by the Killer.",
            "additional_effect": "Assists in locating teammates who need healing."
        },
        "title": "Empathy"
    },
    "m-666-6c740c03b36840d192035a63825db384": {
        "character": "Yun-Jin",
        "img": "assets/dbd/imgs/perks\\m-666-6c740c03b36840d192035a63825db384.png",
        "description": {
            "main_effect": "Whenever another Survivor is hooked, gains 1/2/3 Tokens up to 9/18/27.",
            "secondary_effect": "Each Token grants a 1% progression bonus after a Great Skill Check on a Generator.",
            "additional_effect": "Tokens are consumed after a successful Great Skill Check."
        },
        "title": "Fast Track"
    },
    "z-666-b09908e1c5c8423b80593f6225d3b8f3": {
        "character": "Nancy",
        "img": "assets/dbd/imgs/perks\\z-666-b09908e1c5c8423b80593f6225d3b8f3.png",
        "description": {
            "main_effect": "Increases your walking speed by 10/15/20%.",
            "secondary_effect": "Unlocks the ability to see your own Scratch Marks.",
            "additional_effect": "Useful for stealthy movement."
        },
        "title": "Fixated"
    },
    "c-666-a30294ba7cd04a7c9323c8d911f6c7c1": {
        "character": "Leon",
        "img": "assets/dbd/imgs/perks\\c-666-a30294ba7cd04a7c9323c8d911f6c7c1.png",
        "description": {
            "main_effect": "After repairing Generators for 70/60/50%, activates.",
            "secondary_effect": "Enter a Locker and press the Ability button to craft a Flash Grenade.",
            "additional_effect": "Flashbang is left behind when escaping the Trial."
        },
        "title": "Flashbang"
    },
    "w-666-418efef171fa40b092685cbe4e0e7a7a": {
        "character": "Ash",
        "img": "assets/dbd/imgs/perks\\w-666-418efef171fa40b092685cbe4e0e7a7a.png",
        "description": {
            "main_effect": "While in the Dying State, 50% of your Recovery progress is converted to Wiggle progress up to 40/45/50%.",
            "secondary_effect": "Activated when the Killer picks you up.",
            "additional_effect": "Useful for escape attempts when downed."
        },
        "title": "Flip-Flop"
    },
    "s-666-eff5974f2c1a4648bdef6ff6fffecbf0": {
        "character": "Vittorio",
        "img": "assets/dbd/imgs/perks\\s-666-eff5974f2c1a4648bdef6ff6fffecbf0.png",
        "description": {
            "main_effect": "Succeeding a Great Skill Check while repairing reveals the Killer's Aura to you for 4/5/6 seconds.",
            "secondary_effect": "Focuses on Great Skill Checks to gain insight.",
            "additional_effect": "Helps understand the Killer's movements."
        },
        "title": "Fogwise"
    },
    "i-666-d10b29dcdf424a6cbfc0e4b45962d54f": {
        "character": "Zarina",
        "img": "assets/dbd/imgs/perks\\i-666-d10b29dcdf424a6cbfc0e4b45962d54f.png",
        "description": {
            "main_effect": "While healthy and healing without a Med-Kit, trade 1 Health State with another Survivor.",
            "secondary_effect": "Instantly heals them to Injured or full health while you become injured.",
            "additional_effect": "Causes Broken Status Effect for 80/70/60 seconds."
        },
        "title": "For the People"
    },
    "t-666-fd4ca33bbd04433aaa7369ec6f4db011": {
        "character": "Thalita",
        "img": "assets/dbd/imgs/perks\\t-666-fd4ca33bbd04433aaa7369ec6f4db011.png",
        "description": {
            "main_effect": "Increases your Repair speed, and that of the other Survivor(s) who completed the repairs with you, by +5% for the next 45/60/75 seconds.",
            "secondary_effect": "None",
            "additional_effect": "None"
        },
        "title": "Friendly Competition"
    },
    "x-666-7cf7f1570352499da9c667671bbec7f0": {
        "character": "Jane",
        "img": "assets/dbd/imgs/perks\\x-666-7cf7f1570352499da9c667671bbec7f0.png",
        "description": {
            "main_effect": "When rushing out of a Locker, stun the Killer for 3 seconds if they are within range.",
            "secondary_effect": "Head On causes the Exhausted Status Effect for 60/50/40 seconds.",
            "additional_effect": "Cannot be used when Exhausted or when you have accrued Idle Crows."
        },
        "title": "Head On"
    },
    "d-666-536847f753bc4705a1939439d3f22299": {
        "character": "All",
        "img": "assets/dbd/imgs/perks\\d-666-536847f753bc4705a1939439d3f22299.png",
        "description": {
            "main_effect": "Grants a permanent 5/6/7% Haste Status Effect once the Exit Gates are powered.",
            "secondary_effect": "None",
            "additional_effect": "None"
        },
        "title": "Hope"
    },
    "i-666-d37f5ea7857f4b67aad5778f2eccf1ff": {
        "character": "Rebecca",
        "img": "assets/dbd/imgs/perks\\i-666-d37f5ea7857f4b67aad5778f2eccf1ff.png",
        "description": {
            "main_effect": "After hitting a Great Skill Check while repairing or healing, gains +1 Token up to 6 Tokens.",
            "secondary_effect": "Increases Skill Check Trigger odds, Skill Check Rotation speed, and Bonus progression by varying percentages per Token.",
            "additional_effect": "Loses all Tokens if succeeding a Good Skill Check, failing a Skill Check, or if interrupted."
        },
        "title": "Hyperfocus"
    },
    "r-666-767cd707c1bd4a9fa5b7b6ef5e904491": {
        "character": "Haddie",
        "img": "assets/dbd/imgs/perks\\r-666-767cd707c1bd4a9fa5b7b6ef5e904491.png",
        "description": {
            "main_effect": "Can see Scratch Marks of other Survivors.",
            "secondary_effect": "Reveals the Killer's Aura for 3/4/5 seconds if another Survivor loses a Health State within 32 meters.",
            "additional_effect": "None"
        },
        "title": "Inner Focus"
    },
    "c-666-d0e8a17289ad4cccbb56ceae503d1245": {
        "character": "Nancy",
        "img": "assets/dbd/imgs/perks\\c-666-d0e8a17289ad4cccbb56ceae503d1245.png",
        "description": {
            "main_effect": "Automatically heals 1 Health State while hiding in a Locker for 10/9/8 seconds when injured or suffering from Deep Wound.",
            "secondary_effect": "Does not activate if suffering from the Broken Status Effect.",
            "additional_effect": "None"
        },
        "title": "Inner Strength"
    },
    "x-666-5ee73998add3496bbd7d2900785a0bcd": {
        "character": "Sable",
        "img": "assets/dbd/imgs/perks\\x-666-5ee73998add3496bbd7d2900785a0bcd.png",
        "description": {
            "main_effect": "Permanently reduces the Repair Charges requirement of all Generators in the Trial by 8/9/10 Charges.",
            "secondary_effect": "Automatically enters the Injured State and suffers from the Broken Status Effect for the remainder of the Trial.",
            "additional_effect": "Disables all Invocation Perks after completion."
        },
        "title": "Invocation: Weaving Spiders"
    },
    "p-666-28b4780956d94c62813d076561bb3b6c": {
        "character": "Jake",
        "img": "assets/dbd/imgs/perks\\p-666-28b4780956d94c62813d076561bb3b6c.png",
        "description": {
            "main_effect": "Reduces Grunts of Pain volume by 25/50/75% while in the Injured State.",
            "secondary_effect": "Cannot be used when Exhausted.",
            "additional_effect": "Does not cause the Exhausted Status Effect."
        },
        "title": "Iron Will"
    },
    "m-666-ac2df4196882404a8eda3e3c041a8b67": {
        "character": "All",
        "img": "assets/dbd/imgs/perks\\m-666-ac2df4196882404a8eda3e3c041a8b67.png",
        "description": {
            "main_effect": "While hooked, reveals the Auras of all Survivors to each other and reveals the Killer's Aura if within 8/12/16 meters.",
            "secondary_effect": "While another Survivor is hooked, reveals the Auras of other Survivors and the Killer's Aura if within 8/12/16 meters.",
            "additional_effect": "None"
        },
        "title": "Kindred"
    },
    "n-666-c3daefd54eab4ec7ba5a69aad6bda547": {
        "character": "Dwight",
        "img": "assets/dbd/imgs/perks\\n-666-c3daefd54eab4ec7ba5a69aad6bda547.png",
        "description": {
            "main_effect": "Increases Action speeds of other Survivors by 15/20/25% within 8 meters.",
            "secondary_effect": "Effect lingers for 15 seconds after leaving range.",
            "additional_effect": "Survivors can only be affected by one instance of Leader at a time."
        },
        "title": "Leader"
    },
    "r-666-97664b72cca4480fb536816ca48370b0": {
        "character": "Bill",
        "img": "assets/dbd/imgs/perks\\r-666-97664b72cca4480fb536816ca48370b0.png",
        "description": {
            "main_effect": "When the last Survivor remaining, reveals the Aura of the Hatch within 24/28/32 meters.",
            "secondary_effect": "None",
            "additional_effect": "None"
        },
        "title": "Left Behind"
    },
    "y-666-8f83cc688e874ae6b388ced8ab342916": {
        "character": "Ellen",
        "img": "assets/dbd/imgs/perks\\y-666-8f83cc688e874ae6b388ced8ab342916.png",
        "description": {
            "main_effect": "Suppresses the sound of footsteps while running when healthy.",
            "secondary_effect": "Has a cooldown of 28/24/20 seconds after a Rush Vault.",
            "additional_effect": "None"
        },
        "title": "Light-Footed"
    },
    "w-666-c9d6cd85b28c4c56b4e38cc2863df9b8": {
        "character": "All",
        "img": "assets/dbd/imgs/perks\\w-666-c9d6cd85b28c4c56b4e38cc2863df9b8.png",
        "description": {
            "main_effect": "Reduces Scratch Marks duration by 3/4/5 seconds.",
            "secondary_effect": "Reduces the chance of Scratch Marks patches appearing by -60%.",
            "additional_effect": "None"
        },
        "title": "Lightweight"
    },
    "l-666-6470be3333284df88361ebf4ac537b04": {
        "character": "Feng",
        "img": "assets/dbd/imgs/perks\\l-666-6470be3333284df88361ebf4ac537b04.png",
        "description": {
            "main_effect": "Grants a +50% Haste Status Effect for 3 seconds after a Rushed Vault.",
            "secondary_effect": "Causes the Exhausted Status Effect for 60/50/40 seconds.",
            "additional_effect": "Cannot be used when Exhausted."
        },
        "title": "Lithe"
    },
    "o-666-5d02ee76c037469bb574c19becc0d939": {
        "character": "Ada",
        "img": "assets/dbd/imgs/perks\\o-666-5d02ee76c037469bb574c19becc0d939.png",
        "description": {
            "main_effect": "Suppresses Pools of Blood, Scratch Marks, and Grunts of Pain for 70/80/90 seconds.",
            "secondary_effect": "Activates only when you're the sole healthy Survivor.",
            "additional_effect": "None"
        },
        "title": "Low Profile"
    },
    "z-666-ad248b87630d48e0b78895690048c0ef": {
        "character": "Yui",
        "img": "assets/dbd/imgs/perks\\z-666-ad248b87630d48e0b78895690048c0ef.png",
        "description": {
            "main_effect": "Suppresses Pools of Blood and Scratch Marks for 40/50/60 seconds.",
            "secondary_effect": "Recharges 1 second for every second spent healing another Survivor.",
            "additional_effect": "Deactivates when healthy or in the Dying State."
        },
        "title": "Lucky Break"
    },
    "u-666-b01d9a60ee544f72bd279e0e1988dfa7": {
        "character": "Ellen",
        "img": "assets/dbd/imgs/perks\\u-666-b01d9a60ee544f72bd279e0e1988dfa7.png",
        "description": {
            "main_effect": "Suppresses Grunts of Pain and Pools of Blood for 10 seconds while hiding in a Locker.",
            "secondary_effect": "Reveals the Auras of other Survivors and the closest Generator upon exiting the Locker.",
            "additional_effect": "Has a cooldown of 40/35/30 seconds."
        },
        "title": "Lucky Star"
    },
    "o-666-d2e592ce1ccd4c75bf71f9c2684d63a7": {
        "character": "Gabriel",
        "img": "assets/dbd/imgs/perks\\o-666-d2e592ce1ccd4c75bf71f9c2684d63a7.png",
        "description": {
            "main_effect": "Grants the Endurance Status Effect for 6/8/10 seconds after healing another Survivor.",
            "secondary_effect": "Grants 1/2/3% Haste Status Effect while running and suffering from Deep Wound.",
            "additional_effect": "Endurance is canceled prematurely when performing a Conspicuous Action."
        },
        "title": "Made for This"
    },
    "d-666-b8140a13287044fca7464d0469f2aeb1": {
        "character": "Ash",
        "img": "assets/dbd/imgs/perks\\d-666-b8140a13287044fca7464d0469f2aeb1.png",
        "description": {
            "main_effect": "After three Protection Hits, shields you from going down next time while injured.",
            "secondary_effect": "Reveals your Aura to the Killer if fully healed and more than 12/14/16 meters away.",
            "additional_effect": "Deactivates when put into the Dying State. Increases odds of being Obsession by +100%."
        },
        "title": "Mettle of Man"
    },
    "w-666-966bac588560488092b3338daae849ed": {
        "character": "David",
        "img": "assets/dbd/imgs/perks\\w-666-966bac588560488092b3338daae849ed.png",
        "description": {
            "mainEffect": "You suffer from the Broken Status Effect for the entire Trial.",
            "secondaryEffect": "Pools of Blood are suppressed, and Grunts of Pain are reduced by 25/50/75% when injured or dying.",
            "additionalEffect": "Recovery speed is increased by 15/20/25%, and you can fully recover from the Dying State."
        },
        "title": "No Mither"
    },
    "t-666-60368385656e440486a837a5a28dbc5a": {
        "character": "All",
        "img": "assets/dbd/imgs/perks\\t-666-60368385656e440486a837a5a28dbc5a.png",
        "description": {
            "mainEffect": "Increases your Action speeds in Healing and Unhooking by 30/40/50% when Exit Gates are powered.",
            "secondaryEffect": "Increases the Haste Status Effect of Survivors unhooked by +7%. Reveals the Auras of the other Survivors.",
            "additionalEffect": "Grants 50/75/100% bonus Bloodpoints for actions in the Altruism Category."
        },
        "title": "No One Left Behind"
    },
    "n-666-7a47f2b9f27548b59ca578625389987c": {
        "character": "Laurie",
        "img": "assets/dbd/imgs/perks\\n-666-7a47f2b9f27548b59ca578625389987c.png",
        "description": {
            "mainEffect": "Reveals the Killer's Aura to you whenever the Killer reads your Aura.",
            "secondaryEffect": "Increases Action speeds in Repairing, Healing, and Cleansing by 2/4/6%.",
            "additionalEffect": "Automatically reveals your Aura to the Killer for 3 seconds every 30 seconds when you are the Obsession."
        },
        "title": "Object of Obsession"
    },
    "w-666-fb6f0401c92d4a64b25f8bd651ff0cc5": {
        "character": "Zarina",
        "img": "assets/dbd/imgs/perks\\w-666-fb6f0401c92d4a64b25f8bd651ff0cc5.png",
        "description": {
            "mainEffect": "Prevents your Aura from being revealed to the Killer for 60/70/80 seconds after being unhooked.",
            "secondaryEffect": "Suppresses Grunts of Pain when injured and grants the Endurance Status Effect.",
            "additionalEffect": "Deactivates once the Exit Gates are powered."
        },
        "title": "Off the Record"
    },
    "l-666-b3ed1de6831346ba8132eefce3bbdcd2": {
        "character": "Ace",
        "img": "assets/dbd/imgs/perks\\l-666-b3ed1de6831346ba8132eefce3bbdcd2.png",
        "description": {
            "mainEffect": "Increases the radius of all Aura-reading abilities by 8/12/16 meters.",
            "secondaryEffect": "Survivors can only be affected by one instance at a time."
        },
        "title": "Open-Handed"
    },
    "a-666-2d16508c6f7542d4969b54c90f5b1f35": {
        "character": "Jonah",
        "img": "assets/dbd/imgs/perks\\a-666-2d16508c6f7542d4969b54c90f5b1f35.png",
        "description": {
            "mainEffect": "Extends the duration of the On-hit Speed Boost by +2 seconds.",
            "secondaryEffect": "Causes the Exhausted Status Effect for 60/50/40 seconds.",
            "additionalEffect": "Cannot be used when Exhausted."
        },
        "title": "Overcome"
    },
    "m-666-4a3d561eb13947a7b44c1104c1aade79": {
        "character": "Haddie",
        "img": "assets/dbd/imgs/perks\\m-666-4a3d561eb13947a7b44c1104c1aade79.png",
        "description": {
            "mainEffect": "Increases your Repair speed by 8/9/10% for Dull Totems and by 16/18/20% for Hex Totems.",
            "secondaryEffect": "Deactivates when losing a Health State."
        },
        "title": "Overzealous"
    },
    "g-666-362c3bac968943b88b8bb3f0bf0be099": {
        "character": "Yoichi",
        "img": "assets/dbd/imgs/perks\\g-666-362c3bac968943b88b8bb3f0bf0be099.png",
        "description": {
            "mainEffect": "Suppresses Scratch Marks, Pools of Blood, and Grunts of Pain for 5/6/7 seconds after stunning the Killer.",
            "secondaryEffect": "Suppresses Scratch Marks and Pools of Blood."
        },
        "title": "Parental Guidance"
    },
    "d-666-fa17789786df4b78a9fcecc46fa79474": {
        "character": "Quentin",
        "img": "assets/dbd/imgs/perks\\d-666-fa17789786df4b78a9fcecc46fa79474.png",
        "description": {
            "mainEffect": "Increases Unlocking speed of Chests by 40/60/80% when in the Injured State.",
            "secondaryEffect": "Reduces Hearing range of noises related to Unlocking by -8 meters.",
            "additionalEffect": "Guarantees an Emergency Med-Kit when unlocking a Chest."
        },
        "title": "Pharmacy"
    },
    "q-666-2f0ba4ed41464431ba7723bfcb6adf55": {
        "character": "Nicolas",
        "img": "assets/dbd/imgs/perks\\q-666-2f0ba4ed41464431ba7723bfcb6adf55.png",
        "description": {
            "mainEffect": "Allows you to silently enter the Dying State while crouching and motionless.",
            "secondaryEffect": "Suppresses Grunts of Pain and Pools of Blood.",
            "additionalEffect": "Grants full recovery from the Dying State and heals instantly, granting a +50% Haste Status Effect."
        },
        "title": "Plot Twist"
    },
    "i-666-7a460ea3cc0643a6b5a93bcfdcae1231": {
        "character": "All",
        "img": "assets/dbd/imgs/perks\\i-666-7a460ea3cc0643a6b5a93bcfdcae1231.png",
        "description": {
            "mainEffect": "Reveals the Auras of closed Chests and Items within 16/24/32 meters.",
            "secondaryEffect": "Increases Odds of finding higher Rarity Items in Chests."
        },
        "title": "Plunderer's Instinct"
    },
    "l-666-9cbca42204e84195a4e8c0aeeb1631a2": {
        "character": "Jane",
        "img": "assets/dbd/imgs/perks\\l-666-9cbca42204e84195a4e8c0aeeb1631a2.png",
        "description": {
            "mainEffect": "Prevents leaving Scratch Marks for 6/8/10 seconds after completing a Generator.",
            "secondaryEffect": "Prevents leaving Scratch Marks."
        },
        "title": "Poised"
    },
    "m-666-7fc77db9114244c285922c626d05d644": {
        "character": "Vittorio",
        "img": "assets/dbd/imgs/perks\\m-666-7fc77db9114244c285922c626d05d644.png",
        "description": {
            "mainEffect": "Allows converting 1.5% of Repair progression into 1 Token.",
            "secondaryEffect": "Progresses the Generator by 1% per Token, consuming all Tokens.",
            "additionalEffect": "Deactivates and loses all Tokens upon losing a Health State."
        },
        "title": "Potential Energy"
    },
    "x-666-efd712249d0d4fffbeb86003ee16150c": {
        "character": "\u00c9lodie",
        "img": "assets/dbd/imgs/perks\\x-666-efd712249d0d4fffbeb86003ee16150c.png",
        "description": {
            "mainEffect": "Reveals the Auras of available Pallets while in the Dying State.",
            "secondaryEffect": "Allows dropping a nearby Pallet to stun the Killer and escape their grasp.",
            "additionalEffect": "Deactivates after successful use."
        },
        "title": "Power Struggle"
    },
    "e-666-ef2aa709808344808b6f7a3cc405f0e6": {
        "character": "All",
        "img": "assets/dbd/imgs/perks\\e-666-ef2aa709808344808b6f7a3cc405f0e6.png",
        "description": {
            "mainEffect": "Auditory warning upon looking in the Killer's direction within a 45-degree cone.",
            "secondaryEffect": "Cool-down of 60/45/30 seconds."
        },
        "title": "Premonition"
    },
    "j-666-500156e3fa01477cb805665315e8b108": {
        "character": "Dwight",
        "img": "assets/dbd/imgs/perks\\j-666-500156e3fa01477cb805665315e8b108.png",
        "description": {
            "mainEffect": "Increases Repair speed by 6/8/10% for every other Survivor within 4 meters.",
            "secondaryEffect": "Effect is also applied to other Survivors in range."
        },
        "title": "Prove Thyself"
    },
    "l-666-d6d6a737d3c64a6eb2ba2b9ecb97faa8": {
        "character": "Meg",
        "img": "assets/dbd/imgs/perks\\l-666-d6d6a737d3c64a6eb2ba2b9ecb97faa8.png",
        "description": {
            "mainEffect": "Suppresses Loud Noise Notification triggered by rushing to vault Windows, Pallets, or Lockers.",
            "secondaryEffect": "Has a cool-down of 30/25/20 seconds."
        },
        "title": "Quick & Quiet"
    },
    "o-666-c9f82b3fef5540f889ea87130980ba8f": {
        "character": "Vittorio",
        "img": "assets/dbd/imgs/perks\\o-666-c9f82b3fef5540f889ea87130980ba8f.png",
        "description": {
            "mainEffect": "Reveals Generators' Auras within 36 meters while being chased.",
            "secondaryEffect": "Increases Repair speed of other Survivors by 6/7/8%."
        },
        "title": "Quick Gambit"
    },
    "y-666-f7c42007126a4ae680d025ead335f8af": {
        "character": "Ada",
        "img": "assets/dbd/imgs/perks\\y-666-f7c42007126a4ae680d025ead335f8af.png",
        "description": {
            "mainEffect": "Grants 40/45/50% of your missing Healing Progression when another Survivor loses a Health State within 32 meters.",
            "secondaryEffect": "Only activates when you are in the Injured State."
        },
        "title": "Reactive Healing"
    },
    "j-666-b2114fe5d2184e34a4b006f0e975a030": {
        "character": "Rebecca",
        "img": "assets/dbd/imgs/perks\\j-666-b2114fe5d2184e34a4b006f0e975a030.png",
        "description": {
            "mainEffect": "Halt Sacrifice Process of a hooked Survivor for 20/25/30 seconds.",
            "secondaryEffect": "Pauses Skill Checks if hooked Survivor is in Struggle Phase."
        },
        "title": "Reassurance"
    },
    "g-666-27aaa16b91de4c5d836a4e45c9067a6d": {
        "character": "Zarina",
        "img": "assets/dbd/imgs/perks\\g-666-27aaa16b91de4c5d836a4e45c9067a6d.png",
        "description": {
            "mainEffect": "Highlights a Generator's Aura after repairing for at least 3 seconds.",
            "secondaryEffect": "Entering a Locker triggers a Loud Noise Notification at the highlighted Generator."
        },
        "title": "Red Herring"
    },
    "z-666-419b4604def44b029f7626896afb8ce7": {
        "character": "Cheryl",
        "img": "assets/dbd/imgs/perks\\z-666-419b4604def44b029f7626896afb8ce7.png",
        "description": {
            "mainEffect": "Allows blocking a Generator with The Entity for 30 seconds.",
            "secondaryEffect": "Reveals the Aura of the blocked Generator to all Survivors in white."
        },
        "title": "Repressed Alliance"
    },
    "m-666-c96e455da32f45d2b103dfbc6d1c650d": {
        "character": "Haddie",
        "img": "assets/dbd/imgs/perks\\m-666-c96e455da32f45d2b103dfbc6d1c650d.png",
        "description": {
            "mainEffect": "Grants the ability to rummage through an opened Chest to guarantee a basic Flashlight.",
            "secondaryEffect": "After successfully blinding the Killer, the Killer suffers from the Blindness Status Effect for 20/25/30 seconds."
        },
        "title": "Residual Manifest"
    },
    "g-666-7753d24317884bdf8d2ec8a79e436654": {
        "character": "All",
        "img": "assets/dbd/imgs/perks\\g-666-7753d24317884bdf8d2ec8a79e436654.png",
        "description": {
            "mainEffect": "Increases Action speeds by 3/6/9% when in the Injured State.",
            "secondaryEffect": "Applicable to Repairing, Healing, Sabotaging, Unhooking, Vaulting, and more."
        },
        "title": "Resilience"
    },
    "d-666-4f9302d8a5ad4bf8b65d96eefef171b1": {
        "character": "Jill",
        "img": "assets/dbd/imgs/perks\\d-666-4f9302d8a5ad4bf8b65d96eefef171b1.png",
        "description": {
            "mainEffect": "Instantly gain 40/45/50% of your missing Healing progression after being unhooked or unhooking yourself.",
            "secondaryEffect": "Only activates after unhooking."
        },
        "title": "Resurgence"
    },
    "v-666-e3c331a2910649148a9d248ccff34cca": {
        "character": "Leon",
        "img": "assets/dbd/imgs/perks\\v-666-e3c331a2910649148a9d248ccff34cca.png",
        "description": {
            "mainEffect": "While repairing Generators, succeed 5/4/3 Good or Great Skill Checks to activate Rookie Spirit for the remainder of the Trial.",
            "secondaryEffect": "The Auras of any regressing Generators are revealed to you until they stop regressing.",
            "additionalEffect": "\"I'll stop this, lieutenant. I promise.\" \u2014 Leon Scott Kennedy"
        },
        "title": "Rookie Spirit"
    },
    "r-666-b1c7b7d6ec1d4494b414c80567172c97": {
        "character": "Jake",
        "img": "assets/dbd/imgs/perks\\r-666-b1c7b7d6ec1d4494b414c80567172c97.png",
        "description": {
            "mainEffect": "Unlocks potential in your Aura-reading ability. While the Killer is carrying another Survivor, you see the Aura of every Hook within 56 meters of the pick-up location.",
            "secondaryEffect": "The Auras of regular Hooks are revealed to you in white and Scourge Hooks in yellow. Unlocks the ability to sabotage Hooks without a Toolbox.",
            "additionalEffect": "Sabotaging a Hook without a Toolbox takes 2.3 seconds, with a cool-down of 70/65/60 seconds."
        },
        "title": "Saboteur"
    },
    "f-666-7bc703dfe99f4efbb13d75781cb16336": {
        "character": "Gabriel",
        "img": "assets/dbd/imgs/perks\\f-666-7bc703dfe99f4efbb13d75781cb16336.png",
        "description": {
            "mainEffect": "While holding a depleted Toolbox, Scavenger activates.",
            "secondaryEffect": "Great Repairing Skill Checks grant 1 Token, up to a maximum of 5 Tokens. Reaching maximum Tokens automatically recharges the Toolbox.",
            "additionalEffect": "Recharging reduces Repair speed by -50% for 40/35/30 seconds. Scavenger grants the ability to rummage through an opened Chest once per Trial, guaranteeing a basic Toolbox."
        },
        "title": "Scavenger"
    },
    "s-666-d6bd6dc74bad443d9263f959f98df0b6": {
        "character": "Nicolas",
        "img": "assets/dbd/imgs/perks\\s-666-d6bd6dc74bad443d9263f959f98df0b6.png",
        "description": {
            "mainEffect": "When inside the Terror Radius, looking at the Killer causes you to scream and reveal their Aura for 3/4/5 seconds.",
            "secondaryEffect": "A 50% chance to scream again extends the Aura-reveal duration by another 2 seconds.",
            "additionalEffect": "Scene Partner has a cool-down of 60 seconds."
        },
        "title": "Scene Partner"
    },
    "t-666-3471b067c580465aa0d434e1a7a69eff": {
        "character": "Steve",
        "img": "assets/dbd/imgs/perks\\t-666-3471b067c580465aa0d434e1a7a69eff.png",
        "description": {
            "mainEffect": "When you heal another Survivor for the equivalent of 1 Health State, Second Wind activates.",
            "secondaryEffect": "After being unhooked or unhooking yourself, you suffer from the Broken Status Effect until Second Wind deactivates.",
            "additionalEffect": "Automatically heals 1 Health State after 28/24/20 seconds. Deactivates if healed by Second Wind or if put into the Dying State."
        },
        "title": "Second Wind"
    },
    "c-666-b35b14f4d90e4d729fb48022d6d1d5bd": {
        "character": "Claudette",
        "img": "assets/dbd/imgs/perks\\c-666-b35b14f4d90e4d729fb48022d6d1d5bd.png",
        "description": {
            "mainEffect": "Unlocks the Self-Care ability, allowing you to self-heal without needing a Med-Kit.",
            "secondaryEffect": "Self-heals at 25/30/35% of normal Healing speed.",
            "additionalEffect": ""
        },
        "title": "Self-Care"
    },
    "i-666-3f3f3f1428ba45a093232c3649604034": {
        "character": "Yun-Jin",
        "img": "assets/dbd/imgs/perks\\i-666-3f3f3f1428ba45a093232c3649604034.png",
        "description": {
            "mainEffect": "When another Survivor is hit within 16 meters of you, Self-Preservation activates.",
            "secondaryEffect": "Suppresses Scratch Marks, Grunts of Pain, and Bleeding for 6/8/10 seconds.",
            "additionalEffect": "\"Something I learnt in the industry: when the axe is swinging, keep your head down.\" \u2014 Yun-Jin Lee"
        },
        "title": "Self-Preservation"
    },
    "a-666-677b76cbf7b54fa7af985f631fc97b27": {
        "character": "All",
        "img": "assets/dbd/imgs/perks\\a-666-677b76cbf7b54fa7af985f631fc97b27.png",
        "description": {
            "mainEffect": "Increases the number of available Self-Unhook attempts by +3.",
            "secondaryEffect": "Increases the odds of a successful Self-Unhook attempt by 2/3/4%.",
            "additionalEffect": ""
        },
        "title": "Slippery Meat"
    },
    "z-666-f59bd4d36b804e489e7438032dd912f1": {
        "character": "All",
        "img": "assets/dbd/imgs/perks\\z-666-f59bd4d36b804e489e7438032dd912f1.png",
        "description": {
            "mainEffect": "Receive an auditory warning when looking in the direction of Totems in a 45\u00b0 cone within 8/10/12 meters.",
            "secondaryEffect": "Small Game has a cool-down of 14/12/10 seconds each time it activates.",
            "additionalEffect": "Each Dull or Hex Totem cleansed reduces the Detection cone's angle by 5\u00b0, down to a minimum of 20\u00b0."
        },
        "title": "Small Game"
    },
    "e-666-defdd5319a5d4f02ad455117d4cd116d": {
        "character": "Yun-Jin",
        "img": "assets/dbd/imgs/perks\\e-666-defdd5319a5d4f02ad455117d4cd116d.png",
        "description": {
            "mainEffect": "Stunning the Killer with a Pallet triggers Smash Hit, granting a +50% Haste Status Effect for 4 seconds.",
            "secondaryEffect": "Causes the Exhausted Status Effect for 30/25/20 seconds.",
            "additionalEffect": "\"I have dealt with psychopaths in suits. You're just uglier and worse dressed.\" \u2014 Yun-Jin Lee"
        },
        "title": "Smash Hit"
    },
    "m-666-2dd98db146c74a4889ed367028bddaee": {
        "character": "Laurie",
        "img": "assets/dbd/imgs/perks\\m-666-2dd98db146c74a4889ed367028bddaee.png",
        "description": {
            "mainEffect": "Each time another Survivor is killed, Sole Survivor gains 1 Token up to 3 Tokens.",
            "secondaryEffect": "Grants a radius per Token where you are immune to the Killer's Aura-reading abilities.",
            "additionalEffect": "When the last Survivor, Repair, Gate, and Hatch Opening speeds increase. \"It was the boogeyman.\" \u2014 Laurie Strode"
        },
        "title": "Sole Survivor"
    },
    "i-666-11d6bbc8d7d84259a5c2be45f1713cda": {
        "character": "Jane",
        "img": "assets/dbd/imgs/perks\\i-666-11d6bbc8d7d84259a5c2be45f1713cda.png",
        "description": {
            "mainEffect": "While injured and healing another Survivor without a Med-Kit, you passively heal yourself at 40/45/50% of your Altruistic Healing speed.",
            "secondaryEffect": "",
            "additionalEffect": "\"Showing up when things get rough, listening to people's problems, and supporting those in need; that's how you become stronger, that's how you grow.\" \u2014 Jane Romero"
        },
        "title": "Solidarity"
    },
    "m-666-fd12d29279594654aa32091dfb76d429": {
        "character": "Cheryl",
        "img": "assets/dbd/imgs/perks\\m-666-fd12d29279594654aa32091dfb76d429.png",
        "description": {
            "mainEffect": "After being healed or recovering from the Dying State, grants the Endurance Status Effect for 4/6/8 seconds.",
            "secondaryEffect": "Endurance is cancelled when performing Conspicuous Actions.",
            "additionalEffect": "When Cursed, grants the ability to fully recover from the Dying State. Has a cool-down of 30 seconds."
        },
        "title": "Soul Guard"
    },
    "m-666-a1b3a751c6ce4619bf5caa8108ca8670": {
        "character": "All",
        "img": "assets/dbd/imgs/perks\\m-666-a1b3a751c6ce4619bf5caa8108ca8670.png",
        "description": {
            "mainEffect": "Increases Action speeds in various activities by 2/4/6% when the Killer is within 36 meters and looking at you.",
            "secondaryEffect": "This effect lingers for 0.5 seconds after the Killer loses line of sight.",
            "additionalEffect": "\"There is a voice that doesn't use words. Listen.\" \u2014 Sassy, The Lost Tapes"
        },
        "title": "Spine Chill"
    },
    "u-666-f8e02d89884b480a8afd4b6cf1452daf": {
        "character": "Meg",
        "img": "assets/dbd/imgs/perks\\u-666-f8e02d89884b480a8afd4b6cf1452daf.png",
        "description": {
            "mainEffect": "Starting to run triggers Sprint Burst, granting a +50% Haste Status Effect for 3 seconds.",
            "secondaryEffect": "Causes the Exhausted Status Effect for 60/50/40 seconds.",
            "additionalEffect": "\"See you if you can catch up...\" \u2014 Meg Thomas"
        },
        "title": "Sprint Burst"
    },
    "c-666-c70bcf5e62f44e408759a7c21140f641": {
        "character": "David",
        "img": "assets/dbd/imgs/perks\\c-666-c70bcf5e62f44e408759a7c21140f641.png",
        "description": {
            "mainEffect": "Every 15 seconds within the Killer's Terror Radius while not being chased, Stake Out gains 1 Token.",
            "secondaryEffect": "Good Skill Checks consume 1 Token and are considered Great Skill Checks.",
            "additionalEffect": "\"We're gonna close this case!\" \u2014 Detective David Tapp"
        },
        "title": "Stake Out"
    },
    "z-666-ab695d3da3a745cfba45f5a2da4ec4f7": {
        "character": "Nea",
        "img": "assets/dbd/imgs/perks\\z-666-ab695d3da3a745cfba45f5a2da4ec4f7.png",
        "description": {
            "mainEffect": "Increases the Efficiency of your Items by 15/20/25%.",
            "secondaryEffect": "Extends its effect to other Survivors within 8 meters and lingers for 15 seconds.",
            "additionalEffect": "\"You're doing it wrong! Let me show you how it's done.\" \u2014 Nea Karlsson"
        },
        "title": "Streetwise"
    },
    "n-666-b1f4b11909964d7697ac882fd158468c": {
        "character": "Sable",
        "img": "assets/dbd/imgs/perks\\n-666-b1f4b11909964d7697ac882fd158468c.png",
        "description": {
            "mainEffect": "Unlocks the Strength in Shadows ability to self-heal without a Med-Kit at 70% of normal Healing speed.",
            "secondaryEffect": "After healing in the Basement, reveals the Killer's Aura for 6/8/10 seconds.",
            "additionalEffect": "\"I'm getting out of here, if it's the last thing I do.\" \u2014 Sable"
        },
        "title": "Strength in Shadows"
    },
    "x-666-9a482fb070b84e67a0699d67b08d4f3a": {
        "character": "Renato",
        "img": "assets/dbd/imgs/perks\\x-666-9a482fb070b84e67a0699d67b08d4f3a.png",
        "description": {
            "mainEffect": "After another Survivor finishes healing you, Teamwork activates, suppressing Scratch Marks.",
            "secondaryEffect": "Stays active as long as you both remain within 12 meters of each other or until one of you loses a Health State.",
            "additionalEffect": "Has a cool-down of 180/160/140 seconds. \"I'm good, I'm good... but keep it down.\" \u2014 Renato Lyra"
        },
        "title": "Teamwork: Collective Stealth"
    },
    "e-666-b3ac72b033764150bc1b30815fa043ba": {
        "character": "Thalita",
        "img": "assets/dbd/imgs/perks\\e-666-b3ac72b033764150bc1b30815fa043ba.png",
        "description": {
            "mainEffect": "Whenever you finish healing another Survivor, Teamwork: Power of Two activates, and both you and the healed Survivor benefit from the following effect: Grants a 5% Haste Status Effect for as long as you stay within 12 meters of one another or one of you loses a Health State.",
            "secondaryEffect": "Teamwork: Power of Two has a cool-down of 180/160/140 seconds.",
            "additionalEffect": "Survivors can only be affected by one instance of Teamwork: Power of Two at a time. \"You good? Then keep up!\" \u2014 Thalita Lyra"
        },
        "title": "Teamwork: Power of Two"
    },
    "p-666-1fb6ec39ce69414c8a2013f2d5a8df35": {
        "character": "Feng",
        "img": "assets/dbd/imgs/perks\\p-666-1fb6ec39ce69414c8a2013f2d5a8df35.png",
        "description": {
            "mainEffect": "When repairing a Generator, reduces the audible range of your Repair noises by -8 meters.",
            "secondaryEffect": "Suppresses the explosion and accompanying Loud Noise Notification when failing a Skill Check. Failing a Skill Check instantly regresses the Generator by 5/4/3% of its maximum possible Progression in addition to the default Progression penalty.",
            "additionalEffect": "\"I am gonna stealth this one.\" \u2014 Feng Min"
        },
        "title": "Technician"
    },
    "o-666-e64bb941ac7b4f57a6b8625994b2b36d": {
        "character": "David",
        "img": "assets/dbd/imgs/perks\\o-666-e64bb941ac7b4f57a6b8625994b2b36d.png",
        "description": {
            "mainEffect": "Increases your Crawling speed by 30/40/50%.",
            "secondaryEffect": "Grants the ability to crawl and recover at the same time. Reduces the volume of Grunts of Pain while in the Dying State by -75%.",
            "additionalEffect": "\"What the hell is this? I'm taking this bastard down!\" \u2014 Detective David Tapp"
        },
        "title": "Tenacity"
    },
    "j-666-c76e02e64db34a1291a0f028860a758f": {
        "character": "All",
        "img": "assets/dbd/imgs/perks\\j-666-c76e02e64db34a1291a0f028860a758f.png",
        "description": {
            "mainEffect": "Increases the Success zone of Great Skill Checks while Repairing and Healing by 10/20/30% when in the Injured State.",
            "secondaryEffect": "",
            "additionalEffect": ""
        },
        "title": "This Is Not Happening"
    },
    "u-666-de3745c236c54f34bb81e6c106873d33": {
        "character": "Gabriel",
        "img": "assets/dbd/imgs/perks\\u-666-de3745c236c54f34bb81e6c106873d33.png",
        "description": {
            "mainEffect": "When you are chased by the Killer, the Aura of the Generator with the most progress is revealed to you.",
            "secondaryEffect": "The Aura of the Killer is revealed to you for 4/5/6 seconds after dropping a Pallet. These effects linger for 6/8/10 seconds after ending the Chase, after which Troubleshooter deactivates.",
            "additionalEffect": "\"Nothing gets done around here if I don't do it.\" \u2014 Gabriel Soma"
        },
        "title": "Troubleshooter"
    },
    "c-666-2bcceffb9f4a4070bfe261bd9c759fa6": {
        "character": "Bill",
        "img": "assets/dbd/imgs/perks\\c-666-2bcceffb9f4a4070bfe261bd9c759fa6.png",
        "description": {
            "mainEffect": "Once per Trial, you can completely recover from the Dying State.",
            "secondaryEffect": "Your Recovery speed is increased by 25/30/35%.",
            "additionalEffect": "\"Goddammit, I am seriously FUBAR!\" \u2014 Bill Overbeck"
        },
        "title": "Unbreakable"
    },
    "a-666-fe2c5c680e6648acb7456a036d6c57d3": {
        "character": "Ace",
        "img": "assets/dbd/imgs/perks\\a-666-fe2c5c680e6648acb7456a036d6c57d3.png",
        "description": {
            "mainEffect": "For every Survivor still in the Trial, Up the Ante is granted +1 Token. Increases the odds of every Survivor succeeding a Self-Unhook attempt by a stackable 1/2/3% per Token, up to a maximum of 3/6/9%.",
            "secondaryEffect": "",
            "additionalEffect": "\"What can I say? I'm just a very lucky guy... I'm sure some of it will rub off on you.\" \u2014 Ace Visconti"
        },
        "title": "Up the Ante"
    },
    "r-666-468c81d1e25e43d9a33eba15f3badeb1": {
        "character": "Nea",
        "img": "assets/dbd/imgs/perks\\r-666-468c81d1e25e43d9a33eba15f3badeb1.png",
        "description": {
            "mainEffect": "Increases your Crouching Movement speed by 90/95/100%.",
            "secondaryEffect": "",
            "additionalEffect": "\"The paint is still fresh but I am long gone.\" \u2014 Nea Karlsson"
        },
        "title": "Urban Evasion"
    },
    "k-666-7cf79b87980c47d7a965b371481deb1d": {
        "character": "Quentin",
        "img": "assets/dbd/imgs/perks\\k-666-7cf79b87980c47d7a965b371481deb1d.png",
        "description": {
            "mainEffect": "Increases your Recovery rate from various Status Effects by 20/25/30%.",
            "secondaryEffect": "This effect also applies to all other Survivors within 8 meters of your location and lingers for 15 seconds.",
            "additionalEffect": "\"I am gonna be here when you wake up. You are gonna make it.\" \u2014 Quentin Smith"
        },
        "title": "Vigil"
    },
    "z-666-d32d4fbf453f43dfa666bd4523a8ef4e": {
        "character": "Felix",
        "img": "assets/dbd/imgs/perks\\z-666-d32d4fbf453f43dfa666bd4523a8ef4e.png",
        "description": {
            "mainEffect": "The Auras of Generators are revealed to you within 32 meters.",
            "secondaryEffect": "Each time a Generator is completed, Visionary is deactivated for 20/18/16 seconds.",
            "additionalEffect": ""
        },
        "title": "Visionary"
    },
    "g-666-bcff7dd1fe5f436cb5e54d75c91d8217": {
        "character": "Quentin",
        "img": "assets/dbd/imgs/perks\\g-666-bcff7dd1fe5f436cb5e54d75c91d8217.png",
        "description": {
            "mainEffect": "Once all Generators are completed, Wake Up! activates: The Auras of the Exit Gate Switches are revealed to you within 128 meters. Your Aura is revealed to all other Survivors within 128 meters of your location while opening an Exit Gate.",
            "secondaryEffect": "Increases your Gate Opening speed by 15/20/25%.",
            "additionalEffect": "\"Ok, look. If we survive the next 24 hours, then I'll take you out on a real date.\" \u2014 Quentin Smith"
        },
        "title": "Wake Up!"
    },
    "j-666-2dbae7e997e14b0aa13ae047c2416449": {
        "character": "All",
        "img": "assets/dbd/imgs/perks\\j-666-2dbae7e997e14b0aa13ae047c2416449.png",
        "description": {
            "mainEffect": "Increases your Altruistic Healing speed by 100% for the next 30/60/90 seconds whenever you rescue another Survivor from a Hook.",
            "secondaryEffect": "",
            "additionalEffect": "\"I am confident we can all escape in one piece if we help each other.\""
        },
        "title": "We'll Make It"
    },
    "s-666-68c1434c2cf146b8b346b9e055cae750": {
        "character": "David King",
        "img": "assets/dbd/imgs/perks\\s-666-68c1434c2cf146b8b346b9e055cae750.png",
        "description": {
            "mainEffect": "Increases your Healing speed by 100% when healing a dying Survivor. Performing specific actions grants +1 Token to We're Gonna Live Forever.",
            "secondaryEffect": "Any dying Survivor healed benefits from the Endurance Status Effect for 6/8/10 seconds.",
            "additionalEffect": "\"Come on then, let's ave' it! I don't give a shit pal.\" \u2014 David King"
        },
        "title": "We're Gonna Live Forever"
    },
    "h-666-c3b7098cee54493da77962a86299357e": {
        "character": "Sable",
        "img": "assets/dbd/imgs/perks\\h-666-c3b7098cee54493da77962a86299357e.png",
        "description": {
            "mainEffect": "Grants the ability to successfully unhook yourself when hooked inside the Basement.",
            "secondaryEffect": "The Aura of the Killer is revealed to you for 16/18/20 seconds after unhooking yourself or being unhooked.",
            "additionalEffect": "\"I haven't let anyone get in my way before. You think I'm gonna start now?\" \u2014 Sable"
        },
        "title": "Wicked"
    },
    "e-666-acde84e43f8a4be2a1cdeb0696e13440": {
        "character": "Kate",
        "img": "assets/dbd/imgs/perks\\e-666-acde84e43f8a4be2a1cdeb0696e13440.png",
        "description": {
            "mainEffect": "The Auras of Breakable Walls, Pallets, and Windows are revealed to you within 24/28/32 meters.",
            "secondaryEffect": "",
            "additionalEffect": "\"Rise and shine, work hard, carve out your name, Take aim, pull the trigger, hit the bulls eye for fame, Know the value of faith, an' family, and don't you complain, Open wide, your windows of opportunity\" \u2014 Kate Denson's \"Windows of Opportunity\""
        },
        "title": "Windows of Opportunity"
    },
    "z-666-c5fc05dc2e5940d8a41368987a7a762d": {
        "character": "Ada",
        "img": "assets/dbd/imgs/perks\\z-666-c5fc05dc2e5940d8a41368987a7a762d.png",
        "description": {
            "mainEffect": "After repairing Generators for a total of 50%, Wiretap activates: Press the Active Ability button while near a partially progressed Generator to install a Trap, which stays active for 100/110/120 seconds.",
            "secondaryEffect": "Whenever the Killer comes within 14 meters of the Trapped Generator, their Aura is revealed to all Survivors. Wiretap deactivates after the Generator is damaged or once the timer runs out.",
            "additionalEffect": "The Auras of Trapped Generators are revealed to all Survivors in yellow."
        },
        "title": "Wiretap"
    },
    "u-666-287a15fdf7ae40a188f5da48da028fcf": {
        "character": "Aestri Yazar",
        "img": "assets/dbd/imgs/perks\\u-666-287a15fdf7ae40a188f5da48da028fcf.png",
        "description": {
            "mainEffect": "Press the Active Ability button while standing and motionless to enter the Performance interaction that lasts up to 15 seconds and empowers other Survivors within 16 metres of your location.",
            "secondaryEffect": "The empowering effect depends on the result of you rolling a d20 and lasts for 90 seconds after completing the Performance:\n1: You scream, but without notifying the Killer.\n2 - 10: Skill Checks grant +1 % Progression.\n11 - 19: Skill Checks grant +2 % Progression.\n20: Skill Checks grant +3 % Progression",
            "additionalEffect": "Bardic Inspiration has a cool-down of 60 seconds."
        },
        "title": "Bardic Inspiration"
    },
    "m-666-90fb220c69844519ba6e9ff3caaac293": {
        "character": "Aestri Yazar",
        "img": "assets/dbd/imgs/perks\\m-666-90fb220c69844519ba6e9ff3caaac293.png",
        "description": {
            "mainEffect": "After repairing Generators for a total of 50 %, Mirrored Illusion activates.",
            "secondaryEffect": "Press the Active Ability button when next to either a Chest, Exit Gate, Generator or a Totem to spawn a Static Illusion that lasts for 100/110/120 seconds.",
            "additionalEffect": "Mirrored Illusion deactivates after triggering successfully."
        },
        "title": "Mirrored Illusion"
    },
    "f-666-2d6a211adafb4ffba22ea40b0f4df680": {
        "character": "Aestri Yazar",
        "img": "assets/dbd/imgs/perks\\f-666-2d6a211adafb4ffba22ea40b0f4df680.png",
        "description": {
            "mainEffect": "After standing still for 6/5/4 seconds, Still Sight activates.",
            "secondaryEffect": "While in Still Sight, the Auras of the Killer as well as any Chests and Generators within 24 meters of your location are revealed to you until you start moving again.",
            "additionalEffect": ""
        },
        "title": "Still Sight"
    }
}